torch_pruning/__init__.py
torch_pruning/_helpers.py
torch_pruning/ops.py
torch_pruning/serialization.py
torch_pruning/dependency/__init__.py
torch_pruning/dependency/constants.py
torch_pruning/dependency/dependency.py
torch_pruning/dependency/graph.py
torch_pruning/dependency/group.py
torch_pruning/dependency/index_mapping.py
torch_pruning/dependency/node.py
torch_pruning/dependency/shape_infer.py
torch_pruning/pruner/__init__.py
torch_pruning/pruner/function.py
torch_pruning/pruner/importance.py
torch_pruning/pruner/algorithms/__init__.py
torch_pruning/pruner/algorithms/base_pruner.py
torch_pruning/pruner/algorithms/batchnorm_scale_pruner.py
torch_pruning/pruner/algorithms/compatibility.py
torch_pruning/pruner/algorithms/group_norm_pruner.py
torch_pruning/pruner/algorithms/growing_reg_pruner.py
torch_pruning/pruner/algorithms/scheduler.py
torch_pruning/utils/__init__.py
torch_pruning/utils/benchmark.py
torch_pruning/utils/compute_mat_grad.py
torch_pruning/utils/op_counter.py
torch_pruning/utils/utils.py
torch_pruning-1.6.1.dist-info/licenses/AUTHORS
torch_pruning-1.6.1.dist-info/licenses/LICENSE
torch_pruning-1.6.1.dist-info/METADATA
torch_pruning-1.6.1.dist-info/WHEEL
torch_pruning-1.6.1.dist-info/top_level.txt
torch_pruning-1.6.1.dist-info/RECORD
