Metadata-Version: 2.4
Name: torch-pruning
Version: 1.6.1
Summary: Towards Any Structural Pruning
Home-page: https://github.com/VainF/Torch-Pruning
Author: Gongfan Fang
Author-email: gongfan@u.nus.edu
Project-URL: Bug Reports, https://github.com/VainF/Torch-Pruning/issues
Project-URL: Source, https://github.com/VainF/Torch-Pruning
Project-URL: Documentation, https://github.com/VainF/Torch-Pruning/wiki
Keywords: pytorch,pruning,neural networks,deep learning,optimization
Classifier: Development Status :: 5 - Production/Stable
Classifier: Intended Audience :: Developers
Classifier: Intended Audience :: Science/Research
Classifier: License :: OSI Approved :: MIT License
Classifier: Operating System :: OS Independent
Classifier: Programming Language :: Python :: 3
Classifier: Programming Language :: Python :: 3.7
Classifier: Programming Language :: Python :: 3.8
Classifier: Programming Language :: Python :: 3.9
Classifier: Programming Language :: Python :: 3.10
Classifier: Programming Language :: Python :: 3.11
Classifier: Topic :: Scientific/Engineering :: Artificial Intelligence
Classifier: Topic :: Software Development :: Libraries :: Python Modules
Requires-Python: >=3.7
License-File: LICENSE
License-File: AUTHORS
Requires-Dist: torch>=2.0
Requires-Dist: numpy
Dynamic: author
Dynamic: author-email
Dynamic: classifier
Dynamic: description
Dynamic: description-content-type
Dynamic: home-page
Dynamic: keywords
Dynamic: license-file
Dynamic: project-url
Dynamic: requires-dist
Dynamic: requires-python
Dynamic: summary
